{"Name":"quotedblbase","Format":"1","Advance":{"Width":"466","Depth":false},"Unicode":{"Hex":"201E"},"Contour":[{"Point":[{"X":"50","Y":"195","Z":false,"D":false,"Type":"line"},{"X":"227","Y":"160","Z":false,"D":false,"Type":"line"},{"X":"115","Y":"-136","Z":false,"D":false,"Type":"line"},{"X":"-13","Y":"-107","Z":false,"D":false,"Type":"line"}]},{"Point":[{"X":"261","Y":"195","Z":false,"D":false,"Type":"line"},{"X":"437","Y":"160","Z":false,"D":false,"Type":"line"},{"X":"325","Y":"-136","Z":false,"D":false,"Type":"line"},{"X":"198","Y":"-107","Z":false,"D":false,"Type":"line"}]}]}