{"Name":"igrave","Format":"1","Advance":{"Width":"278","Depth":false},"Unicode":{"Hex":"00EC"},"Contour":[{"Point":[{"X":"93","Y":"0","Z":false,"D":false,"Type":"line"},{"X":"93","Y":"502","Z":false,"D":false,"Type":"line"},{"X":"183","Y":"502","Z":false,"D":false,"Type":"line"},{"X":"183","Y":"0","Z":false,"D":false,"Type":"line"}]},{"Point":[{"X":"2","Y":"740","Z":false,"D":false,"Type":"line"},{"X":"115","Y":"740","Z":false,"D":false,"Type":"line"},{"X":"199","Y":"596","Z":false,"D":false,"Type":"line"},{"X":"137","Y":"596","Z":false,"D":false,"Type":"line"}]}],"Library":{"Key":"com.fontlab.hintData"}}