{"Name":"question","Format":"1","Advance":{"Width":"316","Depth":false},"Unicode":{"Hex":"003F"},"Contour":[{"Point":[{"X":"217","Y":"365","Z":false,"D":false,"Type":"qcurve","Smooth":"yes"},{"X":"173","Y":"321","Z":false,"D":false},{"X":"158","Y":"299","Z":false,"D":false,"Type":"qcurve","Smooth":"yes"},{"X":"133","Y":"261","Z":false,"D":false},{"X":"128","Y":"214","Z":false,"D":false,"Type":"qcurve","Smooth":"yes"},{"X":"128","Y":"208","Z":false,"D":false},{"X":"110","Y":"140","Z":false,"D":false,"Type":"qcurve"},{"X":"68","Y":"201","Z":false,"D":false},{"X":"68","Y":"224","Z":false,"D":false,"Type":"qcurve","Smooth":"yes"},{"X":"68","Y":"334","Z":false,"D":false},{"X":"140","Y":"427","Z":false,"D":false,"Type":"qcurve","Smooth":"yes"},{"X":"178","Y":"476","Z":false,"D":false},{"X":"187","Y":"491","Z":false,"D":false,"Type":"qcurve","Smooth":"yes"},{"X":"207","Y":"527","Z":false,"D":false},{"X":"207","Y":"567","Z":false,"D":false,"Type":"qcurve","Smooth":"yes"},{"X":"207","Y":"644","Z":false,"D":false},{"X":"139","Y":"644","Z":false,"D":false,"Type":"qcurve","Smooth":"yes"},{"X":"102","Y":"644","Z":false,"D":false},{"X":"30","Y":"552","Z":false,"D":false,"Type":"qcurve"},{"X":"6","Y":"626","Z":false,"D":false},{"X":"6","Y":"656","Z":false,"D":false,"Type":"qcurve","Smooth":"yes"},{"X":"6","Y":"679","Z":false,"D":false},{"X":"18","Y":"706","Z":false,"D":false,"Type":"qcurve"},{"X":"181","Y":"706","Z":false,"D":false,"Type":"line","Smooth":"yes"},{"X":"197","Y":"706","Z":false,"D":false},{"X":"239","Y":"672","Z":false,"D":false,"Type":"qcurve","Smooth":"yes"},{"X":"277","Y":"641","Z":false,"D":false},{"X":"284","Y":"629","Z":false,"D":false,"Type":"qcurve","Smooth":"yes"},{"X":"302","Y":"600","Z":false,"D":false},{"X":"302","Y":"542","Z":false,"D":false,"Type":"qcurve","Smooth":"yes"},{"X":"302","Y":"482","Z":false,"D":false},{"X":"275","Y":"436","Z":false,"D":false,"Type":"qcurve","Smooth":"yes"},{"X":"258","Y":"406","Z":false,"D":false}]},{"Point":[{"X":"112","Y":"-7","Z":false,"D":false,"Type":"qcurve","Smooth":"yes"},{"X":"88","Y":"-7","Z":false,"D":false},{"X":"61","Y":"35","Z":false,"D":false},{"X":"61","Y":"60","Z":false,"D":false,"Type":"qcurve","Smooth":"yes"},{"X":"61","Y":"87","Z":false,"D":false},{"X":"93","Y":"141","Z":false,"D":false,"Type":"qcurve"},{"X":"166","Y":"135","Z":false,"D":false},{"X":"166","Y":"68","Z":false,"D":false,"Type":"qcurve","Smooth":"yes"},{"X":"166","Y":"48","Z":false,"D":false},{"X":"151","Y":"22","Z":false,"D":false,"Type":"qcurve","Smooth":"yes"},{"X":"134","Y":"-7","Z":false,"D":false}]}]}