{"Name":"Edieresis","Format":"1","Advance":{"Width":"624","Depth":false},"Unicode":{"Hex":"00CB"},"Contour":[{"Point":[{"X":"313","Y":"900","Z":false,"D":false,"Type":"line"},{"X":"479","Y":"900","Z":false,"D":false,"Type":"line"},{"X":"479","Y":"753","Z":false,"D":false,"Type":"line"},{"X":"313","Y":"753","Z":false,"D":false,"Type":"line"}]},{"Point":[{"X":"91","Y":"900","Z":false,"D":false,"Type":"line"},{"X":"257","Y":"900","Z":false,"D":false,"Type":"line"},{"X":"257","Y":"753","Z":false,"D":false,"Type":"line"},{"X":"91","Y":"753","Z":false,"D":false,"Type":"line"}]},{"Point":[{"X":"33","Y":"706","Z":false,"D":false,"Type":"line"},{"X":"582","Y":"706","Z":false,"D":false,"Type":"line"},{"X":"582","Y":"551","Z":false,"D":false,"Type":"line"},{"X":"233","Y":"551","Z":false,"D":false,"Type":"line"},{"X":"233","Y":"442","Z":false,"D":false,"Type":"line"},{"X":"542","Y":"442","Z":false,"D":false,"Type":"line"},{"X":"542","Y":"293","Z":false,"D":false,"Type":"line"},{"X":"233","Y":"293","Z":false,"D":false,"Type":"line"},{"X":"233","Y":"156","Z":false,"D":false,"Type":"line"},{"X":"587","Y":"156","Z":false,"D":false,"Type":"line"},{"X":"587","Y":"0","Z":false,"D":false,"Type":"line"},{"X":"33","Y":"0","Z":false,"D":false,"Type":"line"}]}]}