{"Name":"p","Format":"1","Advance":{"Width":"640","Depth":false},"Unicode":{"Hex":"0070"},"Contour":[{"Point":[{"X":"45","Y":"544","Z":false,"D":false,"Type":"line"},{"X":"199","Y":"544","Z":false,"D":false,"Type":"line"},{"X":"199","Y":"461","Z":false,"D":false,"Type":"line"},{"X":"207","Y":"474","Z":false,"D":false},{"X":"215","Y":"484","Z":false,"D":false},{"X":"286","Y":"558","Z":false,"D":false},{"X":"382","Y":"558","Z":false,"D":false,"Type":"qcurve","Smooth":"yes"},{"X":"488","Y":"558","Z":false,"D":false},{"X":"613","Y":"407","Z":false,"D":false},{"X":"613","Y":"279","Z":false,"D":false,"Type":"qcurve","Smooth":"yes"},{"X":"613","Y":"152","Z":false,"D":false},{"X":"477","Y":"-12","Z":false,"D":false},{"X":"373","Y":"-12","Z":false,"D":false,"Type":"qcurve","Smooth":"yes"},{"X":"280","Y":"-12","Z":false,"D":false},{"X":"212","Y":"59","Z":false,"D":false,"Type":"qcurve"},{"X":"212","Y":"-202","Z":false,"D":false,"Type":"line"},{"X":"45","Y":"-202","Z":false,"D":false,"Type":"line"}]},{"Point":[{"X":"210","Y":"267","Z":false,"D":false,"Type":"line","Smooth":"yes"},{"X":"210","Y":"202","Z":false,"D":false},{"X":"279","Y":"121","Z":false,"D":false},{"X":"333","Y":"121","Z":false,"D":false,"Type":"qcurve","Smooth":"yes"},{"X":"384","Y":"121","Z":false,"D":false},{"X":"446","Y":"205","Z":false,"D":false},{"X":"446","Y":"275","Z":false,"D":false,"Type":"qcurve","Smooth":"yes"},{"X":"446","Y":"344","Z":false,"D":false},{"X":"383","Y":"427","Z":false,"D":false},{"X":"330","Y":"427","Z":false,"D":false,"Type":"qcurve","Smooth":"yes"},{"X":"276","Y":"427","Z":false,"D":false},{"X":"210","Y":"343","Z":false,"D":false},{"X":"210","Y":"276","Z":false,"D":false,"Type":"qcurve","Smooth":"yes"}]}]}