{"Name":"equal","Format":"1","Advance":{"Width":"584","Depth":false},"Unicode":{"Hex":"003D"},"Contour":[{"Point":[{"X":"37","Y":"314","Z":false,"D":false,"Type":"line"},{"X":"37","Y":"391","Z":false,"D":false,"Type":"line"},{"X":"547","Y":"391","Z":false,"D":false,"Type":"line"},{"X":"547","Y":"314","Z":false,"D":false,"Type":"line"}]},{"Point":[{"X":"37","Y":"111","Z":false,"D":false,"Type":"line"},{"X":"37","Y":"189","Z":false,"D":false,"Type":"line"},{"X":"547","Y":"189","Z":false,"D":false,"Type":"line"},{"X":"547","Y":"111","Z":false,"D":false,"Type":"line"}]}],"Library":{"Key":"com.fontlab.hintData"}}