{"Name":"numbersign","Format":"1","Advance":{"Width":"1314","Depth":false},"Unicode":{"Hex":"0023"},"Contour":[{"Point":[{"X":"1236","Y":"1455","Z":false,"D":false,"Type":"line"},{"X":"1171","Y":"1262","Z":false,"D":false,"Type":"line"},{"X":"1164","Y":"1265","Z":false,"D":false},{"X":"1161","Y":"1266","Z":false,"D":false,"Type":"qcurve","Smooth":"yes"},{"X":"1144","Y":"1273","Z":false,"D":false},{"X":"1142","Y":"1274","Z":false,"D":false,"Type":"qcurve","Smooth":"yes"},{"X":"1130","Y":"1278","Z":false,"D":false},{"X":"1115","Y":"1282","Z":false,"D":false},{"X":"1102","Y":"1282","Z":false,"D":false,"Type":"qcurve","Smooth":"yes"},{"X":"977","Y":"1282","Z":false,"D":false,"Type":"line"},{"X":"902","Y":"1062","Z":false,"D":false,"Type":"line"},{"X":"1008","Y":"1062","Z":false,"D":false,"Type":"line","Smooth":"yes"},{"X":"1018","Y":"1062","Z":false,"D":false},{"X":"1036","Y":"1065","Z":false,"D":false},{"X":"1070","Y":"1072","Z":false,"D":false},{"X":"1090","Y":"1079","Z":false,"D":false,"Type":"qcurve","Smooth":"yes"},{"X":"1097","Y":"1081","Z":false,"D":false},{"X":"1110","Y":"1087","Z":false,"D":false,"Type":"qcurve"},{"X":"1038","Y":"883","Z":false,"D":false,"Type":"line"},{"X":"1033","Y":"887","Z":false,"D":false},{"X":"1031","Y":"889","Z":false,"D":false,"Type":"qcurve","Smooth":"yes"},{"X":"1024","Y":"895","Z":false,"D":false},{"X":"1013","Y":"906","Z":false,"D":false},{"X":"979","Y":"908","Z":false,"D":false},{"X":"977","Y":"908","Z":false,"D":false,"Type":"qcurve","Smooth":"yes"},{"X":"846","Y":"908","Z":false,"D":false,"Type":"line"},{"X":"793","Y":"746","Z":false,"D":false,"Type":"line","Smooth":"yes"},{"X":"787","Y":"730","Z":false,"D":false},{"X":"787","Y":"710","Z":false,"D":false,"Type":"qcurve","Smooth":"yes"},{"X":"787","Y":"690","Z":false,"D":false},{"X":"798","Y":"670","Z":false,"D":false,"Type":"qcurve"},{"X":"564","Y":"670","Z":false,"D":false,"Type":"line"},{"X":"584","Y":"683","Z":false,"D":false},{"X":"600","Y":"704","Z":false,"D":false,"Type":"qcurve","Smooth":"yes"},{"X":"606","Y":"711","Z":false,"D":false},{"X":"610","Y":"717","Z":false,"D":false,"Type":"qcurve","Smooth":"yes"},{"X":"619","Y":"730","Z":false,"D":false},{"X":"623","Y":"744","Z":false,"D":false,"Type":"qcurve","Smooth":"yes"},{"X":"677","Y":"909","Z":false,"D":false,"Type":"line"},{"X":"449","Y":"909","Z":false,"D":false,"Type":"line"},{"X":"396","Y":"753","Z":false,"D":false,"Type":"line","Smooth":"yes"},{"X":"390","Y":"733","Z":false,"D":false},{"X":"390","Y":"714","Z":false,"D":false,"Type":"qcurve","Smooth":"yes"},{"X":"390","Y":"704","Z":false,"D":false},{"X":"393","Y":"688","Z":false,"D":false},{"X":"396","Y":"677","Z":false,"D":false,"Type":"qcurve","Smooth":"yes"},{"X":"396","Y":"675","Z":false,"D":false},{"X":"398","Y":"670","Z":false,"D":false,"Type":"qcurve"},{"X":"176","Y":"670","Z":false,"D":false,"Type":"line"},{"X":"188","Y":"677","Z":false,"D":false},{"X":"202","Y":"688","Z":false,"D":false},{"X":"215","Y":"706","Z":false,"D":false},{"X":"219","Y":"717","Z":false,"D":false,"Type":"qcurve","Smooth":"yes"},{"X":"220","Y":"721","Z":false,"D":false},{"X":"226","Y":"739","Z":false,"D":false,"Type":"qcurve","Smooth":"yes"},{"X":"284","Y":"908","Z":false,"D":false,"Type":"line"},{"X":"142","Y":"908","Z":false,"D":false,"Type":"line","Smooth":"yes"},{"X":"132","Y":"908","Z":false,"D":false},{"X":"113","Y":"907","Z":false,"D":false},{"X":"90","Y":"902","Z":false,"D":false},{"X":"72","Y":"893","Z":false,"D":false,"Type":"qcurve","Smooth":"yes"},{"X":"67","Y":"890","Z":false,"D":false},{"X":"56","Y":"884","Z":false,"D":false,"Type":"qcurve"},{"X":"124","Y":"1088","Z":false,"D":false,"Type":"line"},{"X":"129","Y":"1083","Z":false,"D":false},{"X":"144","Y":"1074","Z":false,"D":false},{"X":"168","Y":"1064","Z":false,"D":false},{"X":"190","Y":"1064","Z":false,"D":false,"Type":"qcurve","Smooth":"yes"},{"X":"337","Y":"1064","Z":false,"D":false,"Type":"line"},{"X":"414","Y":"1281","Z":false,"D":false,"Type":"line"},{"X":"302","Y":"1281","Z":false,"D":false,"Type":"line","Smooth":"yes"},{"X":"276","Y":"1281","Z":false,"D":false},{"X":"251","Y":"1279","Z":false,"D":false},{"X":"229","Y":"1273","Z":false,"D":false,"Type":"qcurve","Smooth":"yes"},{"X":"217","Y":"1270","Z":false,"D":false},{"X":"186","Y":"1257","Z":false,"D":false},{"X":"185","Y":"1257","Z":false,"D":false,"Type":"qcurve","Smooth":"yes"},{"X":"250","Y":"1451","Z":false,"D":false,"Type":"line"},{"X":"256","Y":"1446","Z":false,"D":false},{"X":"260","Y":"1444","Z":false,"D":false,"Type":"qcurve","Smooth":"yes"},{"X":"272","Y":"1437","Z":false,"D":false},{"X":"295","Y":"1429","Z":false,"D":false},{"X":"310","Y":"1429","Z":false,"D":false,"Type":"qcurve","Smooth":"yes"},{"X":"315","Y":"1429","Z":false,"D":false},{"X":"337","Y":"1431","Z":false,"D":false},{"X":"344","Y":"1431","Z":false,"D":false,"Type":"qcurve","Smooth":"yes"},{"X":"464","Y":"1431","Z":false,"D":false,"Type":"line"},{"X":"514","Y":"1574","Z":false,"D":false,"Type":"line","Smooth":"yes"},{"X":"521","Y":"1592","Z":false,"D":false},{"X":"535","Y":"1631","Z":false,"D":false},{"X":"535","Y":"1649","Z":false,"D":false,"Type":"qcurve","Smooth":"yes"},{"X":"535","Y":"1666","Z":false,"D":false},{"X":"532","Y":"1690","Z":false,"D":false},{"X":"530","Y":"1692","Z":false,"D":false,"Type":"qcurve","Smooth":"yes"},{"X":"745","Y":"1692","Z":false,"D":false,"Type":"line"},{"X":"738","Y":"1686","Z":false,"D":false},{"X":"735","Y":"1683","Z":false,"D":false,"Type":"qcurve","Smooth":"yes"},{"X":"722","Y":"1671","Z":false,"D":false},{"X":"717","Y":"1665","Z":false,"D":false,"Type":"qcurve","Smooth":"yes"},{"X":"707","Y":"1651","Z":false,"D":false},{"X":"701","Y":"1634","Z":false,"D":false,"Type":"qcurve","Smooth":"yes"},{"X":"629","Y":"1431","Z":false,"D":false,"Type":"line"},{"X":"858","Y":"1431","Z":false,"D":false,"Type":"line"},{"X":"919","Y":"1611","Z":false,"D":false,"Type":"line","Smooth":"yes"},{"X":"922","Y":"1620","Z":false,"D":false},{"X":"929","Y":"1639","Z":false,"D":false},{"X":"929","Y":"1647","Z":false,"D":false,"Type":"qcurve","Smooth":"yes"},{"X":"929","Y":"1653","Z":false,"D":false},{"X":"925","Y":"1677","Z":false,"D":false},{"X":"909","Y":"1692","Z":false,"D":false,"Type":"qcurve"},{"X":"1142","Y":"1692","Z":false,"D":false,"Type":"line"},{"X":"1135","Y":"1687","Z":false,"D":false},{"X":"1132","Y":"1684","Z":false,"D":false,"Type":"qcurve","Smooth":"yes"},{"X":"1122","Y":"1675","Z":false,"D":false},{"X":"1110","Y":"1654","Z":false,"D":false},{"X":"1099","Y":"1633","Z":false,"D":false},{"X":"1093","Y":"1615","Z":false,"D":false,"Type":"qcurve","Smooth":"yes"},{"X":"1030","Y":"1431","Z":false,"D":false,"Type":"line"},{"X":"1142","Y":"1431","Z":false,"D":false,"Type":"line","Smooth":"yes"},{"X":"1153","Y":"1431","Z":false,"D":false},{"X":"1158","Y":"1431","Z":false,"D":false,"Type":"qcurve","Smooth":"yes"},{"X":"1180","Y":"1431","Z":false,"D":false},{"X":"1184","Y":"1432","Z":false,"D":false,"Type":"qcurve","Smooth":"yes"},{"X":"1186","Y":"1433","Z":false,"D":false},{"X":"1205","Y":"1442","Z":false,"D":false,"Type":"qcurve","Smooth":"yes"}]},{"Point":[{"X":"804","Y":"1281","Z":false,"D":false,"Type":"line"},{"X":"578","Y":"1281","Z":false,"D":false,"Type":"line"},{"X":"503","Y":"1064","Z":false,"D":false,"Type":"line"},{"X":"732","Y":"1064","Z":false,"D":false,"Type":"line"}]}]}